swcli/__init__.py
swcli/films.py
swcli/models.py
swcli/people.py
swcli/planets.py
swcli/settings.py
swcli/species.py
swcli/starships.py
swcli/swcli.py
swcli/utils.py
swcli/vehicles.py
swcli-0.1.88.dist-info/entry_points.txt
swcli-0.1.88.dist-info/WHEEL
swcli-0.1.88.dist-info/METADATA
swcli-0.1.88.dist-info/RECORD
