Metadata-Version: 2.1
Name: swcli
Version: 0.1.88
Summary: A simple CLI to do queries in StarWars API.
Author: Pery Lemke
Author-email: pery.lemke@gmail.com
Requires-Python: >=3.8,<4.0
Classifier: Programming Language :: Python :: 3
Classifier: Programming Language :: Python :: 3.10
Classifier: Programming Language :: Python :: 3.8
Classifier: Programming Language :: Python :: 3.9
Requires-Dist: autopep8 (>=1.5.7,<2.0.0)
Requires-Dist: fire (>=0.4.0,<0.5.0)
Requires-Dist: httpx (>=0.20.0,<0.21.0)
Requires-Dist: pydantic (>=1.8.2,<2.0.0)
